MANIFEST.in
NOTICE.txt
README.rst
bootstrap.py
buildout.cfg
jpl.mcl.site.policy.sublime-project
setup.py
docs/HISTORY.txt
docs/INSTALL.txt
docs/LICENSE.txt
src/jpl/__init__.py
src/jpl.mcl.site.policy.egg-info/PKG-INFO
src/jpl.mcl.site.policy.egg-info/SOURCES.txt
src/jpl.mcl.site.policy.egg-info/dependency_links.txt
src/jpl.mcl.site.policy.egg-info/entry_points.txt
src/jpl.mcl.site.policy.egg-info/namespace_packages.txt
src/jpl.mcl.site.policy.egg-info/not-zip-safe
src/jpl.mcl.site.policy.egg-info/requires.txt
src/jpl.mcl.site.policy.egg-info/top_level.txt
src/jpl/mcl/__init__.py
src/jpl/mcl/site/__init__.py
src/jpl/mcl/site/policy/__init__.py
src/jpl/mcl/site/policy/configure.zcml
src/jpl/mcl/site/policy/testing.py
src/jpl/mcl/site/policy/upgrades.py
src/jpl/mcl/site/policy/upgrades.zcml
src/jpl/mcl/site/policy/profiles/default/metadata.xml
src/jpl/mcl/site/policy/profiles/default/properties.xml
src/jpl/mcl/site/policy/profiles/default/registry.xml
src/jpl/mcl/site/policy/tests/__init__.py
src/jpl/mcl/site/policy/tests/test_setup.py