Metadata-Version: 2.1
Name: jpl.mcl.site.policy
Version: 1.0.1
Summary: Policy package for MCL
Home-page: http://mcl.jpl.nasa.gov/software/jpl.mcl.site.policy
Author: Sean Kelly
Author-email: sean.kelly@jpl.nasa.gov
Maintainer: Sean Kelly
Maintainer-email: sean.kelly@jpl.nasa.gov
License: Proprietary
Download-URL: http://oodt.jpl.nasa.gov/dist/mcl/jpl.mcl.site.policy-1.0.1.tar.gz
Keywords: plone zope site mcl policy dependency
Platform: UNKNOWN
Classifier: Development Status :: 2 - Pre-Alpha
Classifier: Environment :: Web Environment
Classifier: Framework :: Plone
Classifier: License :: Other/Proprietary License
Classifier: Operating System :: OS Independent
Classifier: Programming Language :: Python
Classifier: Topic :: Internet :: WWW/HTTP
Classifier: Topic :: Software Development :: Libraries :: Python Modules
Provides-Extra: test
